<?xml version='1.0' encoding='UTF-8'?><magicdraw><trigger id="_2022x_1_6580223_1727475088612_1978_95910" refElementId="_2022x_1_6580223_1727475088612_1978_95910" humanType="Trigger" classType="Trigger" requireSort="node" icon="AOMS_files/icon_trigger_12608060.jpg"><visibility humanName="Visibility">public</visibility><qualifiedName humanName="Qualified Name">Spacecraft Mission Context::6 Spacecraft::Behavior::System States::System States::::on::::Operating::::::</qualifiedName><owner refid="_2022x_1_6580223_1727475076175_380661_95905" refElementId="_2022x_1_6580223_1727475076175_380661_95905" humanType="Transition" classType="Transition" name="Transition:De-orbit complete[Spacecraft Mission Context::6 Spacecraft::Behavior::System States::System States::::on::::Operating::::deorbiting -> Spacecraft Mission Context::6 Spacecraft::Behavior::System States::System States::::]" isRelationship="true" icon="AOMS_files/icon_transition_1339440195.jpg" humanName="Owner" mode="s,e"/><name humanName="Name" mode="s,e"></name><event refid="_2022x_1_6580223_1727475088612_540484_95909" refElementId="_2022x_1_6580223_1727475088612_540484_95909" humanType="Signal Event" classType="SignalEvent" name="SignalEvent De-orbit complete" icon="AOMS_files/icon_signalevent_1962468501.jpg" humanName="Event"/><documentation humanName="Documentation"></documentation><TO_DO humanName="To Do"></TO_DO><ActiveHyperlink humanName="Active Hyperlink"></ActiveHyperlink><eventType humanName="Event Type" mode="s,e">SignalEvent</eventType><report_appliedStereotype_tags humanName="Applied Stereotype" requireSort="element" mode="s,e"/></trigger></magicdraw>